jupyagent/__init__.py
jupyagent/docker/Dockerfile
jupyagent/docker/__init__.py
jupyagent/docker/jupyter_settings.json
jupyagent/docker/opencode.json.template
jupyagent/docker/register-kernel.sh
jupyagent/docker/run-jupyter-mcp.sh
jupyagent/docker/start.sh
jupyagent/docker/supervisord.conf
jupyagent/main.py
jupyagent-0.3.1.dist-info/licenses/LICENSE
jupyagent-0.3.1.dist-info/WHEEL
jupyagent-0.3.1.dist-info/entry_points.txt
jupyagent-0.3.1.dist-info/METADATA
jupyagent-0.3.1.dist-info/RECORD
