Metadata-Version: 2.4
Name: jupyagent
Version: 0.3.1
Summary: One-command installer for Jupyter + LLM agent sandbox
License-Expression: MIT
License-File: LICENSE
Requires-Dist: rich>=13.7.0
Requires-Dist: questionary>=2.0.0
Requires-Python: >=3.9
